Workbook

Sheet Unit Details 
B3: مجموعة سيد فياض العالمية ش م م
B4: SYED FAYYAZ GROUP INTERNATIONAL L L C
B5: ص.ب: 154 ، الرمز البريدي : 111 ، سلطنة عمان ، هاتف : 2449944841 968 + ، فاكس 24497482 968 +
B6: P.O.Box : 154 , P.C : 111 ,Sultanate of Oman, Tel.: +968 24499481 Fax.: +968 24497482
B8: Unit Details
B9: Location,Building | C9: ='01- Residential'!C23 -> MQ Plot 369, Building 5240
B10: Unit (Flat, Shop) | C10: ='01- Residential'!C24 -> Flat
B11: Floor Details | C11: ='01- Residential'!C25 -> Third Floor
B12: Serial Number | C12: ='01- Residential'!C26 -> 301
B13: Electricity Account Number | C13: ='01- Residential'!C27 -> Q137673
B14: Water Account Number | C14: ='01- Residential'!C28 -> 90517548

Sheet Index Commercial - 02
B5: مجموعة سيد فياض العالمية ش م م
B6: SYED FAYYAZ GROUP INTERNATIONAL L L C
B7: ص.ب: 154 ، الرمز البريدي : 111 ، سلطنة عمان ، هاتف : 2449944841 968 + ، فاكس 24497482 968 +
B8: P.O.Box : 154 , P.C : 111 ,Sultanate of Oman, Tel.: +968 24499481 Fax.: +968 24497482
B10: Index
B11: Page NO | C11: Details
B12: 1 | C12: Municipal Agreement
B13: 2 | C13: Tenancy Agreement Addendum
B14: 3 | C14: Personal Guarantee Form
B15: 4 | C15: Declaration Form
B16: 5 | C16: Tenant Check-In
B17: 6 | C17: ID / Passport
B18: 7 | C18: CR Papers
B19: 8 | C19: PDC Cheque copies

Sheet 01- Residential
A4: مجموعة سيد فياض العالمية ش م م
A5: SYED FAYYAZ GROUP INTERNATIONAL L L C
A6: ص.ب: 154 ، الرمز البريدي : 111 ، سلطنة عمان ، هاتف : 2449944841 968 + ، فاكس 24497482 968 +
A7: P.O.Box : 154 , P.C : 111 ,Sultanate of Oman, Tel.: +968 24499481 Fax.: +968 24497482
A9: RENT A UNIT ( Documents No 1 ) | D9: تأجير وحدة ( مستند رقم 1 )
A10: Type | C10: New جديد | E10: النوع
A11: Agreement No.: | C11: 20241115892 | E11: رقم العقد :
A12: Landlord Details (First Party): | D12: بيانات المؤجر(الطرف الأول ) :
A13: Name: | C13: سيد فياض بن علي - Syed Fayyaz ali | E13: الاسم:
A14: Tenant Details (Second Party): | D14: بيانات المستأجر (الطرف الثاني ) :
A15: Contract Type | C15: سكني Residential | E15: نوع العقد
A16: Name: | C16: Ljina Sultan Sulaiman AlMahrouqi | E16: أسم المستأجر
A17: ID / Labor Card No.: | C17: 5640721 | E17: الرقم المدني / رقم بطاقة العمل :
A18: Passport number: | E18: رقم الجواز :
A19: Mobile No: | D19: 91707091 | E19: رقم النقال :
A20: Alternative phone number: | E20: رقم الهاتف البديل :
A21: E-mail : | E21: البريد الإكتروني :
A22: Property Details: | D22: بيانات العقار المستأجر :
A23: Building No.: | C23: MQ Plot 369, Building 5240 | E23: رقم المبنى :
A24: Unit (Flat,Office,Shop) | C24: Flat | E24: الوحدة (شقة ، مكتب ، محل)
A25: Floor Details | C25: Third Floor | E25: تفاصيل الطابق :
A26: Flat/Shop no : | C26: 301 | E26: رقم الشقة/المحل :
A27: Electricity Meter Number | C27: Q137673 | E27: رقم عداد الكهرباء :
A28: Water Meter Number | C28: 90517548 | E28: رقم عداد الماء :
A29: Agreement Period & Rental Value: | D29: مدة العقد والقيمة الإيجارية :
A30: Monthly Rental Amount : | C30: 325 | E30: القيمة الإيجارية الشهرية :
A31: This agreement is valid for a period of (months) : | C31: 12 | E31: يسري هذا العقد لمدة بالأشهر :
A32: Municipal fees | C32: =(C30*C31)*3% -> 117 | E32: رسوم البلدية :
A33: From : | C33: 45992 | E33: يبدأ من :
A34: To : | C34: 46356 | E34: ينتهي في :
A35: other details | D35: تفاصيل أخرى
A36: Payment Method | C36: شيك CHQ | E36: طريقة الدفع :
A37: Security | C37: تحويل بنكي Bank transfer | E37: الضمان :
A38: check or receipt number | C38: 4355 | E38: رقم الشيك أو الإيصال :
A39: Deposit amount: | C39: 325 | E39: مبلغ المودع :
A40: Remarks | D40: الملاحظات :
A43: Other terms and conditions | D43: شروط وأحكام أخرى :
A44: 1 | B44: This form is an integral part of the lease agreement, the municipal contract, and the terms of the lease, and by signing it, I agree to register the lease with the applicable terms or what will be updated by the property management.(To view the terms and conditions, scan the barcode or request a digital copy via WhatsApp 93555643) | D44: هذا النموذج هو جزء لا يتجزأ من اتفاقية الإيجار ، وعقد البلدية ، وشروط الإيجار ، وبتوقيعه ، أوافق على تسجيل عقد الإيجار بالشروط المعمول بهاء أو ما سيتم تحديثه من قبل إدارة العقار. ( للإطلاع على الشروط والقوانين أمسح الباركود او اطلب نسخة رقمية عبر الواتساب 93555643 ) | F44: 1
A45: 2 | B45: The tenant's signature on this form constitutes approval of the contract documentation by the competent authorities. | D45: توقيع المستأجر على هذا النموذج موافقة على توثيق العقد من قبل السلطات المختصة. | F45: 2

Sheet 01- Renewal
A4: مجموعة سيد فياض العالمية ش م م
A5: SYED FAYYAZ GROUP INTERNATIONAL L L C
A6: ص.ب: 154 ، الرمز البريدي : 111 ، سلطنة عمان ، هاتف : 2449944841 968 + ، فاكس 24497482 968 +
A7: P.O.Box : 154 , P.C : 111 ,Sultanate of Oman, Tel.: +968 24499481 Fax.: +968 24497482
A9: RENT A UNIT ( Documents No 1 ) | D9: تأجير وحدة ( مستند رقم 1 )
A10: Type | C10: تجديد Renewal | E10: النوع
A11: Agreement No.: | C11: ='01- Residential'!C11 -> 20241115892 | E11: رقم العقد :
A12: Landlord Details (First Party): | D12: بيانات المؤجر(الطرف الأول ) :
A13: Name: | C13: ='01- Residential'!C13 -> سيد فياض بن علي - Syed Fayyaz ali | E13: الاسم:
A14: Tenant Details (Second Party): | D14: بيانات المستأجر (الطرف الثاني ) :
A15: Contract Type | C15: ='01- Residential'!C15 -> سكني Residential | E15: نوع العقد
A16: Name: | C16: ='01- Residential'!C16 -> Ljina Sultan Sulaiman AlMahrouqi | E16: أسم المستأجر
A17: ID / Labor Card No.: | C17: ='01- Residential'!C17 -> 5640721 | E17: الرقم المدني / رقم بطاقة العمل :
A18: Mobile No: | D18: ='01- Residential'!D19 -> 91707091 | E18: رقم النقال :
A19: Property Details: | D19: بيانات العقار المستأجر :
A20: Building No.: | C20: ='01- Residential'!C23 -> MQ Plot 369, Building 5240 | E20: رقم المبنى :
A21: Unit (Flat,Office,Shop) | C21: ='01- Residential'!C24 -> Flat | E21: الوحدة (شقة ، مكتب ، محل)
A22: Flat/Shop no : | C22: ='01- Residential'!C26 -> 301 | E22: رقم الشقة/المحل :
A23: Agreement Period & Rental Value: | D23: مدة العقد والقيمة الإيجارية :
A24: Monthly Rental Amount : | C24: ='01- Residential'!C30 -> 325 | E24: القيمة الإيجارية الشهرية :
A25: This agreement is valid for a period of (months) : | C25: ='01- Residential'!C31 -> 12 | E25: يسري هذا العقد لمدة بالأشهر :
A26: Municipal fees | C26: ='01- Residential'!C32 -> 117 | E26: رسوم البلدية :
A27: From : | C27: ='01- Residential'!C33 -> 45992 | E27: يبدأ من :
A28: To : | C28: ='01- Residential'!C34 -> 46356 | E28: ينتهي في :
A29: Remarks | D29: الملاحظات :
A32: Other terms and conditions | D32: شروط وأحكام أخرى :
A33: 1 | B33: This form is an integral part of the rental agreement, the municipal contract, and the applicable rental conditions, and by signing it, I agree to renew the rental contract with the same previous conditions or what will be updated by the property management. | D33: هذا النموذج هو جزء لا يتجزأ من اتفاقية الإيجار ، وعقد البلدية ، وشروط الإيجار المعمول بها ، وبتوقيعه ، أوافق على تجديد عقد الإيجار بنفس الشروط السابقة أو ما سيتم تحديثه من قبل إدارة العقار. | F33: 1
A34: 2 | B34: I declare to myself that I am the signatory of this contract that I have read, viewed and agreed to all the terms and laws in force in the Sayed Fayyaz Group International and related to leasing. (To view the terms and conditions, scan the barcode or request a digital copy via WhatsApp 93555643) | D34: أقرعلى نفسي أنا الموقع على هذا العقد بإنني قد قرأت وأطلعت ووافقت على كافة الشروط و القوانين المعمول بهاء في مجموعة سيد فياض العالمية و الخاصة بالتأجير . ( للإطلاع على الشروط والقوانين أمسح الباركود او اطلب نسخة رقمية عبر الواتساب 93555643 ). | F34: 2

Sheet 02- Extension of Tenancy
A4: مجموعة سيد فياض العالمية ش م م
A5: SYED FAYYAZ GROUP INTERNATIONAL L L C
A6: ص.ب: 154 ، الرمز البريدي : 111 ، سلطنة عمان ، هاتف : 2449944841 968 + ، فاكس 24497482 968 +
A7: P.O.Box : 154 , P.C : 111 ,Sultanate of Oman, Tel.: +968 24499481 Fax.: +968 24497482
A9: Extension of Tenancy Agreement (Document No. 2-A ) | D9: ملحق عقد إيجار ( مستند رقم 2 - أ )
A10: Agreement No.: | C10: ='01- Residential'!C11 -> 20241115892 | E10: رقم العقد :
A11: Other terms and conditions | D11: شروط وأحكام أخرى :
A12: 1 | B12: Official Communication Method | D12: طريقة الاتصال الرسمية | F12: 1
A13: A | B13: All official communication must be delivered in writing by hand or the registered email addresses in this agreement. | D13: يجب تسليم جميع المراسلات الرسمية الكتابة باليد أو عناوين البريد الإلكتروني المسجلة في هذه الاتفاقية. | F13: أ
A14: 2 | B14: Non-Refundable Booking Deposit | D14: وديعة الحجز غير قابلة للاسترداد | F14: 2
A15: A | B15: In case the Tenant does not proceed with renting the Unit, the non-refundable booking deposit will be forfeited. | D15: في حالة عدم قيام المستأجر باستئجار الوحدة ، سيتم مصادرة وديعة الحجز غير القابلة للاسترداد. | F15: أ
A16: B | B16: Once this agreement is signed and the Tenant has paid the rent for the first month of the tenancy agreement, the non-refundable booking deposit will automatically be converted to a security deposit. | D16: بمجرد توقيع هذه الاتفاقية ودفع المستأجر إيجار الشهر الأول من اتفاقية الإيجار ، سيتم تحويل وديعة الحجز غير القابلة للاسترداد تلقائيًا إلى وديعة تأمين. | F16: ب
A17: 3 | B17: Security Deposit | D17: مبلغ التأمين | F17: 3
A18: A | B18: The Tenant is required to deposit and maintain one month’s rent as a security deposit throughout the tenancy period. | D18: يتعين على المستأجر إيداع إيجار شهر واحد والاحتفاظ به كوديعة ضمان طوال فترة الإيجار. | F18: أ
A19: B | B19: The security deposit is refundable subject to the Tenant completing their full tenancy period as per the agreement and clearing all their dues. | D19: وديعة الضمان قابلة للاسترداد بشرط استكمال المستأجر لفترة الإيجار الكاملة وفقًا للاتفاقية وتسوية جميع مستحقاته. | F19: ب
A20: C | B20: If the tenancy agreement is terminated early for any reason, the security deposit will be forfeited. | D20: إذا تم إنهاء عقد الإيجار مبكرًا لأي سبب من الأسباب ، فسيتم مصادرة وديعة التأمين. | F20: ت
A21: 4 | B21: Payment Terms | D21: شروط الدفع | F21: 4
A22: A | B22: The Tenant must pay the due rent on the 01st of the month in advance. | D22: يجب على المستأجر دفع الإيجار المستحق في اليوم الأول من الشهر مقدمًا. | F22: أ
A23: B | B23: The Tenant must provide post-dated cheques for the entire duration of the tenancy agreement. | D23: يجب على المستأجر تقديم شيكات مؤجلة الدفع لكامل مدة عقد الإيجار. | F23: ب
A24: C | B24: The Tenant must provide 3 additional open-dated cheques equivalent to 3 months of rent. These will be deposited by the Landlord in case of any outstanding rent or other dues. | D24: يجب على المستأجر تقديم 3 شيكات إضافية مفتوحة الدفع تعادل 3 أشهر من الإيجار. سيتم إيداعها من قبل المالك في حالة وجود أي إيجار مستحق أو مستحقات أخرى. | F24: ت
A25: D | B25: If the Tenant prefers to pay the rent by a bank transfer instead, the payment should be cleared at least three working days prior to the rent due date. Moreover, the Tenant should inform the Landlord once the bank transfer is completed by an official communication method. | D25: إذا فضل المستأجر دفع الإيجار عن طريق التحويل المصرفي بدلاً من ذلك ، فيجب تسوية الدفع قبل ثلاثة أيام عمل على الأقل من تاريخ استحقاق الإيجار. علاوة على ذلك ، يجب على المستأجر إبلاغ المالك بمجرد اكتمال التحويل المصرفي بطريقة اتصال رسمية. | F25: ث
A26: E | B26: The cheque deposit date is the 01st of the month. In case the Tenant’s cheque bounces on the 01st, the Landlord will deposit it again on the 10th of the month, unless the Tenant has cleared the rent by bank transfer prior to the 10th. | D26: تاريخ إيداع الشيك هو الأول من الشهر. في حالة ارتداد الشيك الخاص بالمستأجر في اليوم الأول ، سيقوم المالك بإيداعه مرة أخرى في اليوم العاشر من الشهر ، إلا إذا قام المستأجر بتخليص الإيجار عن طريق التحويل المصرفي قبل اليوم العاشر. | F26: ج
A27: F | B27: If the Tenant's cheques bounce due to insufficient funds, a penalty of 5% of the cheque amount will be charged by the Landlord. | D27: إذا ارتد شيك المستأجر بسبب عدم كفاية الأموال ، سيتم فرض غرامة قدرها 5 ٪ من مبلغ الشيك من قبل المالك. | F27: ح
A28: 5 | B28: Late Payments | D28: المدفوعات المتأخرة | F28: 5
A29: A | B29: If the rent is not received by the 15th of the month, a 15% late fee penalty will be charged on the cheque value on the 15th of the month. | D29: إذا لم يتم استلام الإيجار بحلول الخامس عشر من الشهر ، فسيتم فرض غرامة تأخير قدرها 15٪ على قيمة الشيك في الخامس عشر من الشهر. | F29: أ
A30: B | B30: An additional 1% late fee penalty will be charged for every additional day of delay in rent after the 15th of the month, .e.g. a 17% late fee penalty if the rent is not paid until the 17th of the month. | D30: سيتم فرض غرامة إضافية بنسبة 1٪ على رسوم التأخير عن كل يوم تأخير إضافي في الإيجار بعد اليوم الخامس عشر من الشهر ، على سبيل المثال. غرامة 17٪ رسوم تأخير إذا لم يتم دفع الإيجار حتى 17 من الشهر. | F30: ب
A31: C | B31: If the late fee penalty is not paid by the end of the month, it will carry forward and accumulate with future penalty fees. | D31: إذا لم يتم دفع غرامة الرسوم المتأخرة بحلول نهاية الشهر ، فسيتم ترحيلها وتتراكم مع رسوم الغرامات المستقبلية. | F31: ت
A32: 6 | B32: Utility Bills | D32: فواتير المياه والكهرباء | F32: 6
A33: A | B33: The Tenant is required to pay all utility bills of their Unit in full every month. | D33: يتعين على المستأجر دفع جميع فواتير المرافق الخاصة بوحدته بالكامل كل شهر. | F33: أ
A34: B | B34: If the Tenant’s combined bills for water and electricity accumulate to over 25% of their monthly rent, the Landlord has the right to disconnect the electricity and water of the Unit and take legal action. The pending bill amount may also be deducted from the security deposit.With the tenant bearing all the legal consequences and losses that he may incur as a result of cutting the service for him. | D34: إذا تراكمت فواتير المستأجر المجمعة للمياه والكهرباء لأكثر من 25٪ من الإيجار الشهري ، يحق للمالك فصل الكهرباء والمياه عن الوحدة واتخاذ الإجراءات القانونية. قد يتم أيضًا خصم مبلغ الفاتورة المعلقة من وديعة التأمين. مع تحمل المستأجر كافة التبعات القانونية والخسائر التي قد يتكبدها نتيجة قطع الخدمة عنه. | F34: ب
A35: C | B35: In case the Landlord pays the utility bills on the Tenant's behalf, a service charge of 5% of the monthly rent will be charged. | D35: في حالة قيام المالك بدفع فواتير الخدمات نيابة عن المستأجر ، سيتم فرض رسوم خدمة بنسبة 5٪ من الإيجار الشهري. | F35: ت
A36: 7 | B36: Conditions of Stay | D36: شروط الاقامة | F36: 7
A37: A | B37: The Tenant shall abide by all the instructions issued by the Landlord, which may change throughout the tenancy agreement. | D37: يجب على المستأجر الالتزام بجميع التعليمات الصادرة عن المالك ، والتي قد تتغير خلال عقد الإيجار. | F37: أ
A38: B | B38: The Tenant is not allowed to sublet the Unit. | D38: لا يجوز للمستأجر تأجير الوحدة من الباطن. | F38: ب
A39: C | B39: The Unit will be occupied only by the Tenant and their immediate family, and used only for residential purposes. | D39: سيتم شغل الوحدة من قبل المستأجر وعائلته المباشرة فقط ، وسيتم استخدامها فقط للأغراض السكنية. | F39: ت
A40: D | B40: The Tenant will not make any changes to the leased Unit without approval from the Landlord. In case any changes are made without the Landlord's approval, the Landlord has the right to cancel the tenancy agreement. | D40: لن يقوم المستأجر بإجراء أي تغييرات على الوحدة المؤجرة دون موافقة المالك. في حالة إجراء أي تغييرات دون موافقة المالك ، يحق للمالك إلغاء عقد الإيجار. | F40: ث
A41: E | B41: The Tenant must return the Unit at the end of their tenancy agreement in the original condition that they received it in at the start of the tenancy agreement. Failure to do so will require the Landlord to charge all the costs to the Tenant to do such work. | D41: يجب على المستأجر إعادة الوحدة في نهاية عقد الإيجار إلى الحالة الأصلية التي استلمها بها في بداية عقد الإيجار. إن عدم القيام بذلك سوف يتطلب من المالك تحميل جميع التكاليف على المستأجر للقيام بهذا العمل. | F41: ج
A42: F | B42: The Tenant will be liable for any damage occurring to their Unit or the entire Property which is done by the Tenant or the Tenant’s guests or invitees. | D42: سيكون المستأجر مسؤولاً عن أي ضرر يحدث لوحدته أو العقار بأكمله والذي يحدث من قبل المستأجر أو ضيوف المستأجر أو المدعوين. | F42: ح
A43: G | B43: The Tenant will not place any items outside of their leased Unit, including but not limited to the public areas, such as corridors, elevators, staircase, basements and roof floor. | D43: لن يضع المستأجر أي عناصر خارج الوحدة المؤجرة ، بما في ذلك على سبيل المثال لا الحصر المناطق العامة ، مثل الممرات والمصاعد والسلالم والطوابق السفلية وأرضية السقف. | F43: خ
A44: H | B44: The Tenant shall maintain the property in a manner which conforms to all health and safety requirements. The Tenant shall keep their Unit free from all rodents, insects, and vermin attracted by unsanitary conditions caused by Tenant, and shall be responsible for all damage caused by such conditions. | D44: يجب على المستأجر صيانة العقار بطريقة تتوافق مع جميع متطلبات الصحة والسلامة. يجب على المستأجر الحفاظ على وحدته خالية من جميع القوارض والحشرات والحشرات التي تجذبها الظروف غير الصحية التي يسببها المستأجر ، ويكون مسؤولاً عن جميع الأضرار التي تسببها هذه الظروف. | F44: د
A45: I | B45: The Tenant will not litter or throw garbage in any part of the entire Property, or throw anything out of the windows, doors or ventilating ducts. | D45: لا يجوز للمستأجر إلقاء القمامة أو إلقاء القمامة في أي جزء من العقار بأكمله ، أو إلقاء أي شيء من النوافذ أو الأبواب أو قنوات التهوية. | F45: ذ
A46: J | B46: The Tenant shall not permit or allow any vehicles that belong to or are controlled by the Tenant or their employees, suppliers, customers or invitees to be loaded, unloaded or parked in the Property in areas not approved by the Landlord. Not abiding by this will be classified as a Parking Violation. | D46: يجب ألا يسمح المستأجر أو يسمح بأي مركبات تخص المستأجر أو يتحكم فيه أو موظفيه أو مورديه أو زبائنه أو مدعويهم أو تفريغها أو ركنها في العقار في مناطق لم يوافق عليها المالك. عدم الالتزام بهذا سوف يصنف على أنه مخالفة وقوف. | F46: ر
A47: K | B47: The Tenant will not cause excessive noise and disturbances to other occupants of the Property, especially during late hours. The Landlord will notify the Tenant of such complaints. | D47: لن يتسبب المستأجر في إحداث ضوضاء وإزعاج مفرطة لشاغلي العقار الآخرين ، خاصة خلال ساعات العمل المتأخرة. يقوم المالك بإخطار المستأجر بهذه الشكاوى. | F47: ز
A48: 8 | B48: Violations of Conditions | D48: مخالفات الشروط | F48: 8
A49: A | B49: In case the Tenant does not abide by any conditions of stay, the Landlord has the right to impose a penalty of 5% of the monthly rent per violation, per day. | D49: في حالة عدم التزام المستأجر بأي شروط للإقامة ، يحق للمالك فرض غرامة قدرها 5٪ من الإيجار الشهري لكل مخالفة في اليوم. | F49: أ
A50: B | B50: If the Tenant does not resolve the violation immediately, a daily penalty of 5% of the monthly rent will be imposed for each day the violation continues. | D50: إذا لم يقم المستأجر بحل المخالفة على الفور ، سيتم فرض غرامة يومية قدرها 5٪ من الإيجار الشهري عن كل يوم تستمر فيه المخالفة. | F50: ب
A51: C | B51: If a specific violation exceeds 1 month from the date of warning, or if the Tenant receives signicant violations during their tenancy period, the Landlord has the right to terminate the lease agreement and the Tenant should vacate the unit immediately. Failure to do so will result in legal action being taken. | D51: إذا تجاوز الانتهاك المحدد شهرًا واحدًا من تاريخ التحذير ، أو إذا تلقى المستأجر انتهاكات جسيمة خلال فترة الإيجار ، يحق للمالك إنهاء عقد الإيجار ويجب على المستأجر إخلاء الوحدة على الفور. سيؤدي عدم القيام بذلك إلى اتخاذ إجراءات قانونية. | F51: ت
A52: D | B52: In case of a Parking Violation by the Tenant, along with the daily penalty of 5% of the monthly rent, the Landlord shall have the right, without notice, to remove or tow away the vehicle involved and charge the costs to the Tenant. | D52: في حالة مخالفة المستأجر لوقوف السيارات ، بالإضافة إلى الغرامة اليومية البالغة 5٪ من الإيجار الشهري ، يحق للمالك ، دون سابق إنذار ، إزالة أو سحب السيارة المعنية وتحميل التكاليف على المستأجر. | F52: ث
A53: 9 | B53: Access Cards and Building Amenities | D53: بطاقات الوصول ووسائل الراحة في المبنى | F53: 9
A54: A | B54: The Landlord has the right to disconnect the Tenant's building access cards and all other amenities anytime in case the Tenant does not by abide by any of their tenancy requirements. | D54: يحق للمالك فصل بطاقات الوصول إلى المبنى الخاصة بالمستأجر وجميع وسائل الراحة الأخرى في أي وقت في حالة عدم التزام المستأجر بأي من متطلبات الإيجار الخاصة بهم. | F54: أ
A55: 10 | B55: Legal Action | D55: إجراءات قانونية | F55: 10
A56: A | B56: The Tenant will be liable for all legal expenses borne by the Landlord in case of any violation of this tenancy. | D56: سيكون المستأجر مسؤولاً عن جميع النفقات القانونية التي يتحملها المالك في حالة حدوث أي انتهاك لهذا الإيجار. | F56: أ
A57: 11 | B57: Maintenance and Repairs | D57: الصيانة والتصليح | F57: 11
A58: A | B58: Tenant agrees to keep their Unit clean and takes responsibility for damages, window cleaning and all minor repairs. Minor repairs include replacing batteries, light bulbs and tubes. | D58: يوافق المستأجر على الحفاظ على نظافة وحدته ويتحمل مسؤولية الأضرار وتنظيف النوافذ وجميع الإصلاحات الطفيفة. تشمل الإصلاحات البسيطة استبدال البطاريات والمصابيح الكهربائية والأنابيب. | F58: أ
A59: 12 | B59: Right of Entry | D59: حق الدخول | F59: 12
A60: A | B60: In case of emergencies, the Landlord will attempt to contact the Tenant. If no response is received, the Landlord has the right to enter the Unit. | D60: في حالة الطوارئ ، سيحاول المالك الاتصال بالمستأجر. في حالة عدم تلقي أي رد ، يحق للمالك دخول الوحدة. | F60: أ
A61: 13 | B61: Tenancy Renewal | D61: تجديد الإيجار | F61: 13
A62: A | B62: The Landlord has the right to increase the monthly rent indefinitely during the tenancy renewal. | D62: للمالك الحق في زيادة الإيجار الشهري إلى أجل غير مسمى خلال تجديد عقد الإيجار. | F62: أ
A63: B | B63: Before renewing the tenancy agreement, the Tenant will provide all required documentation, security deposit and post-dated cheques. Without these, the Tenant will be unable to renew their tenancy agreement. | D63: قبل تجديد عقد الإيجار ، سيقدم المستأجر جميع المستندات المطلوبة ووديعة الضمان والشيكات المؤجلة. بدون هذه الشروط ، لن يتمكن المستأجر من تجديد عقد الإيجار الخاص به. | F63: ب
A64: C | B64: In case of a delay in renewal of the tenancy agreement due to the Tenant, the Tenant will be liable for the Muncipality renewal fee and all Municipality fines. | D64: في حالة التأخير في تجديد عقد الإيجار بسبب المستأجر ، سيكون المستأجر مسؤولاً عن رسوم تجديد البلدية وجميع غرامات البلدية. | F64: ت
A65: 14 | B65: Vacating the Unit | D65: إخلاء الوحدة | F65: 14
A66: A | B66: The Tenant must complete the full period of the tenancy agreement. | D66: يجب على المستأجر إكمال الفترة الكاملة لعقد الإيجار. | F66: أ
A67: B | B67: If the Tenant wishes to vacate the Unit at the end of their tenancy agreement, a 90-day notice must be given to the Landlord by an official communication method. | D67: إذا رغب المستأجر في إخلاء الوحدة في نهاية عقد الإيجار ، فيجب تقديم إشعار لمدة 90 يومًا إلى المالك من خلال وسيلة اتصال رسمية. | F67: ب
A68: C | B68: If the tenant gives less than a 90-day notice to vacate the Unit at the end of their tenancy agreement, the Tenant will be liable for rent for 90 days from the date of their official notice. | D68: إذا قدم المستأجر إشعارًا مدته أقل من 90 يومًا لإخلاء الوحدة في نهاية اتفاقية الإيجار ، فسيكون المستأجر مسؤولاً عن الإيجار لمدة 90 يومًا من تاريخ إخطاره الرسمي. | F68: ت
A69: D | B69: The Landlord has the right to refuse the handover of the Unit after the end of the tenancy period if the Tenant has not cleared all their dues in full, including but not limited to: rent, utility bills and penalty fees. | D69: يحق للمالك رفض تسليم الوحدة بعد نهاية فترة الإيجار إذا لم يقم المستأجر بتصفية جميع مستحقاته بالكامل ، بما في ذلك على سبيل المثال لا الحصر: الإيجار وفواتير الخدمات ورسوم الغرامات. | F69: ث
A70: E | B70: The Tenant will be obligated to pay rent and utility bills until the handover is completed by the Landlord. | D70: يلتزم المستأجر بدفع فواتير الإيجار والمرافق حتى اكتمال التسليم من قبل المالك. | F70: ج
A71: 15 | B71: Handover of Unit | D71: تسليم الوحدة | F71: 15
A72: A | B72: The Tenant must complete the handover form and return all keys and access cards to the Landlord's office before the tenancy agreement can be ended. The Landlord will issue a clearance form once this is completed. Without the clearance form, the Tenant will continue to be liable for all dues, including rent and utility bills. | D72: يجب على المستأجر إكمال نموذج التسليم وإعادة جميع المفاتيح وبطاقات الوصول إلى مكتب المالك قبل إنهاء عقد الإيجار. سيصدر المالك استمارة براءة ذمة بمجرد اكتمال ذلك. بدون نموذج التخليص ، سيظل المستأجر مسؤولاً عن جميع المستحقات ، بما في ذلك فواتير الإيجار والمرافق. | F72: أ
A73: B | B73: The Tenant must return the Unit in the same condition that it was received at the start of the tenancy. Failure to do so will result in charges to the Tenant. | D73: يجب على المستأجر إعادة الوحدة بنفس الحالة التي تم استلامها بها في بداية عقد الإيجار. سيؤدي عدم القيام بذلك إلى فرض رسوم على المستأجر. | F73: ب
A74: C | B74: The Tenant must have the Unit deep cleaned prior to handover. Failure to do so will result in a cleaning fee charged to the Tenant. | D74: يجب على المستأجر تنظيف الوحدة بعمق قبل التسليم. سيؤدي عدم القيام بذلك إلى فرض رسوم تنظيف على المستأجر. | F74: ت
A75: D | B75: The Tenant will be responsible for any damages to the Unit or overall Property. | D75: سيكون المستأجر مسؤولاً عن أي أضرار تلحق بوحدة الملكية العامة. | F75: ث
A76: E | B76: If the Tenant does not handover the Unit after the expiration of the tenancy agreement, they will be liable for a penalty fee of 3% of the monthly rent for every day, as well as the actual rent value for that period. | D76: إذا لم يسلم المستأجر الوحدة بعد انتهاء عقد الإيجار ، فسيكون مسؤولاً عن دفع غرامة قدرها 3٪ من الإيجار الشهري لكل يوم ، بالإضافة إلى قيمة الإيجار الفعلية لتلك الفترة. | F76: ج
A77: 16 | B77: Fees and Taxes | D77: الرسوم والضرائب | F77: 16
A78: A | B78: The Tenant is liable for all fees and taxes imposed by the government, including but not limited to VAT. | D78: المستأجر مسؤول عن جميع الرسوم والضرائب التي تفرضها الحكومة ، بما في ذلك على سبيل المثال لا الحصر ضريبة القيمة المضافة. | F78: أ
A79: 17 | B79: Severability Clause | D79: شرط الفصل | F79: 17
A80: A | B80: In case any provision in this agreement shall be invalid, the validity of the remaining terms and conditions shall not be impaired in any way. | D80: في حالة عدم صلاحية أي حكم في هذه الاتفاقية ، لن يتم المساس بصلاحية الشروط والأحكام المتبقية بأي شكل من الأشكال. | F80: أ

Sheet Invoice + Requirement
A4: مجموعة سيد فياض العالمية ش م م
A5: SYED FAYYAZ GROUP INTERNATIONAL L L C
A6: ص.ب: 154 ، الرمز البريدي : 111 ، سلطنة عمان ، هاتف : 2449944841 968 + ، فاكس 24497482 968 +
A7: P.O.Box : 154 , P.C : 111 ,Sultanate of Oman, Tel.: +968 24499481 Fax.: +968 24497482
A8: VATIN OM1100300282
A9: Requirement | D9: المتطلبات
A10: Agreement No.: | C10: ='01- Residential'!C11 -> 20241115892 | E10: رقم العقد :
A11: Tenant Name: | C11: ='01- Residential'!C16 -> Ljina Sultan Sulaiman AlMahrouqi | E11: أسم المستأجر
A12: # | B12: تاريخ الشيك - Checks date | C12: مبلغ الإيجار - Rental Amount | D12: الضريبة - VAT | E12: مبلغ الشيك - Check amount
A13: 1 | B13: 45992 | C13: 325 | D13: 0 | E13: =C13 -> 325
A14: 2 | B14: 46023 | C14: 325 | D14: 0 | E14: =C14 -> 325
A15: 3 | B15: 46054 | C15: 325 | D15: 0 | E15: =C15 -> 325
A16: 4 | B16: 46082 | C16: 325 | D16: 0 | E16: =C16 -> 325
A17: 5 | B17: 46113 | C17: 325 | D17: 0 | E17: =C17 -> 325
A18: 6 | B18: 46143 | C18: 325 | D18: 0 | E18: =C18 -> 325
A19: 7 | B19: 46174 | C19: 325 | D19: 0 | E19: =C19 -> 325
A20: 8 | B20: 46204 | C20: 325 | D20: 0 | E20: =C20 -> 325
A21: 9 | B21: 46235 | C21: 325 | D21: 0 | E21: =C21 -> 325
A22: 10 | B22: 46266 | C22: 325 | D22: 0 | E22: =C22 -> 325
A23: 11 | B23: 46296 | C23: 325 | D23: 0 | E23: =C23 -> 325
A24: 12 | B24: 46327 | C24: 325 | D24: 0 | E24: =C24 -> 325
A25: 13 | B25: 45474 | C25: 245 | D25: 0 | E25: 240
A26: Details of checks and additional amounts | D26: تفاصيل الشيكات والمبالغ الإضافية
A27: # | B27: التاريخ - date | C27: المبلغ - Amount | D27: الضريبة - VAT | E27: الإجمالي - Total | F27: طريقة الدفع - Payment method
A28: 1 | B28: Security deposit | C28: 240 | D28: 0 | E28: 240 | F28: نقدأ Cash | G28: شيك Check
A29: 2 | G29: نقدأ Cash
A30: 3 | G30: تحويل - Transfer
A31: 4
A32: 5
A33: 6
A34: Requirement | D34: المتطلبات
A35: 1 | B35: Rent Cheques | F35: 1
A36: 2 | B36: ID Card | F36: 2
A37: 3 | B37: Rent Cheques | F37: 3
A38: 4 | F38: 4
A39: 5 | F39: 5
A40: Notes | D40: الملاحظات :
A41: The Rent cheques should be under Mohammad Syed Fayyaz Ali name شيكات الايجار يجب عن تكون بإسم محمد سيد فياض علي
A43: Other terms and conditions | D43: شروط وأحكام أخرى :
A44: 1 | B44: This document is considered part of the contract, and it must be read with it. | D44: يعتبر هذا المستند جزء من العقد ، ويقرا معه . | F44: 1

Sheet 03- Declaration Form
B5: مجموعة سيد فياض العالمية ش م م
B6: SYED FAYYAZ GROUP INTERNATIONAL L L C
B7: ص.ب: 154 ، الرمز البريدي : 111 ، سلطنة عمان ، هاتف : 2449944841 968 + ، فاكس 24497482 968 +
B8: P.O.Box : 154 , P.C : 111 ,Sultanate of Oman, Tel.: +968 24499481 Fax.: +968 24497482
A10: Declaration Form | E10: إقـــــــــــــــــــــــــــــرار
A11: I, the undersigned do hereby declare that the address mentioned hereunder is mu correct address for the purpose of sending all notices, correspondences, and publications. | E11: بهذا ا أقر أنا الموقع أدناه بأن العنوان الموضح أدناه هو عنوان الاقامة الصحيح لي لتوجيه كافة المراسلات و الإعلانات و الإخطارات إليه .
A12: I do hereby undertake to give notice / inform to the company in case of any change in my address mentioned below within seven days from the date of such change, otherwise my pervious recorded address in my company’s records shall be considered as my address for correspondence. | E12: كما أتعهد بإن أخطر الشركة في حالة حدوث أي تغيير في عنواني المذكور خلال سبعة أيام من تاريخ حدوث ذلك التغيير وإلا أعتبر عنواني السابق المسجل بسجلات الشركة عنواناً وصحيحاً لي للمراسلات
A14: PERMANENT ADDRESS | E14: العنوان الدائم
A15: Wilayat: | C15: Region: | F15: المنطقة : | H15: الولاية :
A16: Village: | C16: Way No: | F16: رقم السكة : | H16: قرية :
A17: Street : | C17: Building No: | F17: رقم المبنى / المنزل : | H17: الشارع :
A18: Nearest Landmark: | H18: أقرب معلم :
A19: GSM No : | C19: Office No : | F19: الهاتف النقال : | H19: هاتف المنزل :
A20: E-mail : | H20: البريد الإلكتروني
A21: Post Box | C21: PC | F21: الرمز البريدي : | H21: صندوق البريد :
A23: CURRENT ADDRESS (If different from the above address) | E23: العنوان الحالي : ( إذا كان مختلفاً عن العنوان المذكور أعلاه )
A24: Wilayat: | C24: Region: | F24: المنطقة : | H24: الولاية :
A25: Village: | C25: Way No: | F25: رقم السكة : | H25: قرية :
A26: Street : | C26: Building No: | F26: رقم المبنى / المنزل : | H26: الشارع :
A27: Nearest Landmark: | H27: أقرب معلم :
A28: GSM No : | C28: Office No : | F28: الهاتف النقال : | H28: هاتف المنزل :
A29: E-mail : | H29: البريد الإلكتروني
A30: Post Box | C30: PC | F30: الرمز البريدي : | H30: صندوق البريد :
A32: Name: | C32: ='01- Residential'!C16 -> Ljina Sultan Sulaiman AlMahrouqi | G32: الأسم :
A33: Civil No : | C33: ='01- Residential'!C17 -> 5640721 | G33: الرقم المدني :
A34: Passport number: | C34: ='01- Residential'!C18 -> 0 | G34: رقم الجواز :
A36: Signature : | G36: التوقيع :
A38: Date : | G38: التاريخ :

Sheet 04- Tenant Check-In
B3: مجموعة سيد فياض العالمية ش م م
B4: SYED FAYYAZ GROUP INTERNATIONAL L L C
B5: ص.ب: 154 ، الرمز البريدي : 111 ، سلطنة عمان ، هاتف : 2449944841 968 + ، فاكس 24497482 968 +
B6: P.O.Box : 154 , P.C : 111 ,Sultanate of Oman, Tel.: +968 24499481 Fax.: +968 24497482
B8: Tenant Check-In (Document No. 4 ) | E8: تسجيل دخول المستأجر ( مستند رقم 4 )
B9: Landlord Details (First Party): | E9: بيانات المؤجر(الطرف الأول ) :
B10: Name: | C10: ='01- Residential'!C13 -> سيد فياض بن علي - Syed Fayyaz ali | G10: الاسم:
B11: Tenant Details (Second Party): | E11: بيانات المستأجر (الطرف الثاني ) :
B12: Contract Type | C12: ='01- Residential'!C15 -> سكني Residential | G12: نوع العقد
B13: Name: | C13: ='01- Residential'!C16 -> Ljina Sultan Sulaiman AlMahrouqi | G13: أسم المستأجر
B14: ID / Labor Card No.: | C14: ='01- Residential'!C17 -> 5640721 | G14: الرقم المدني / رقم بطاقة العمل :
B15: Unit details: | E15: بيانات العقار:
B16: Building No.: | C16: ='01- Residential'!C23 -> MQ Plot 369, Building 5240 | G16: رقم المبنى :
B17: Flat/Shop no : | C17: ='01- Residential'!C26 -> 301 | G17: رقم الشقة/المحل :
B18: Furniture and appliances: | E18: الأثاث والأجهزة :
B19: Description | C19: العلامة التجارية Brand | D19: الحالة Condition | F19: العدد Number | G19: وصف
D20: لا يعمل Invalid | E20: صالح Valid
B21: AC | G21: أجهزة التكييف
B22: AC remote | G22: جهاز التحكم بالتكييف
B23: Fire extinguishers | G23: طفايات الحريق
B24: Fire blanket | G24: بطانية الحريق
B25: Ceiling fans | G25: مراوح السقف
B26: Exhaust fans | G26: مراوح الشفط
B27: Lighting | G27: الإنارة
B28: Water heater | G28: سخان الماء
B29: Doors | G29: الأبواب
B30: Windows | G30: النوافذ
B31: Keys | G31: المفاتيح
B32: Internet router | G32: جهاز توجيه الإنترنت
... B35: Remarks | G35: الملاحظات :
B36: ………………………………………………………………………………………………………………………………………………………………………………
B37: ………………………………………………………………………………………………………………………………………………………………………………
B38: ………………………………………………………………………………………………………………………………………………………………………………
B39: ………………………………………………………………………………………………………………………………………………………………………………
B41: Terms and conditions | E41: شروط وأحكام :
B42: This form is an integral part of and complements the subsequent rental agreement and all subsequent documents. It is referred to as Document #4. | E42: هذه الاستمارة هي جزء لا يتجزأ من اتفاقية الإيجار اللاحقة ويكملها وجميع الوثائق اللاحقة. يشار إليه باسم المستند رقم 4 .

Sheet 05- Tenant Check- out
A4: مجموعة سيد فياض العالمية ش م م
A5: SYED FAYYAZ GROUP INTERNATIONAL L L C
A6: ص.ب: 154 ، الرمز البريدي : 111 ، سلطنة عمان ، هاتف : 2449944841 968 + ، فاكس 24497482 968 +
A7: P.O.Box : 154 , P.C : 111 ,Sultanate of Oman, Tel.: +968 24499481 Fax.: +968 24497482
A9: Tenant Check- out (Document No. 5 ) | D9: تسجيل خروج المستأجر ( مستند رقم 5 )
A10: Landlord Details (First Party): | D10: بيانات المؤجر(الطرف الأول ) :
A11: Name: | B11: سيد فياض بن علي - Syed Fayyaz ali | F11: الاسم:
A12: Tenant Details (Second Party): | D12: بيانات المستأجر (الطرف الثاني ) :
A13: Contract Type | B13: ='01- Residential'!C15 -> سكني Residential | F13: نوع العقد
A14: Name: | B14: ='01- Residential'!C16 -> Ljina Sultan Sulaiman AlMahrouqi | F14: أسم المستأجر
A15: ID / Labor Card No.: | B15: ='01- Residential'!C17 -> 5640721 | F15: الرقم المدني / رقم بطاقة العمل :
A16: Unit details: | D16: بيانات العقار:
A17: Building No.: | B17: ='01- Residential'!C23 -> MQ Plot 369, Building 5240 | F17: رقم المبنى :
A18: Flat/Shop no : | B18: ='01- Residential'!C26 -> 301 | F18: رقم الشقة/المحل :
A19: Electricity Meter Number | B19: S123224 | F19: رقم عداد الكهرباء :
A20: Water Meter Number | B20: 90508853 | F20: رقم عداد الماء :
A21: Eviction date and readings: | D21: تاريخ الإخلاء و القراءات :
A22: Eviction date : | B22: 42370 | F22: تاريخ الإخلاء :
A23: Electricity Meter Reading : | B23: 0 | F23: قراءة عداد الكهرباء :
A24: Bill amount : | B24: 0 | F24: مبلغ الفاتورة :
A25: Water Meter Reading : | B25: 0 | F25: قراءة عداد الماء :
A26: Bill amount : | B26: 0 | F26: مبلغ الفاتورة :
A27: Furniture and appliances: | D27: الأثاث والأجهزة :
A28: Description | B28: العلامة التجارية Brand | C28: الحالة Condition | E28: العدد Number | F28: وصف
C29: لا يعمل Invalid | D29: صالح Valid
A30: AC | F30: أجهزة التكييف
A31: AC remote | F31: جهاز التحكم بالتكييف
A32: Fire extinguishers | F32: طفايات الحريق
A33: Fire blanket | F33: بطانية الحريق
A34: Ceiling fans | F34: مراوح السقف
A35: Exhaust fans | F35: مراوح الشفط
A36: Lighting | F36: الإنارة
A37: Water heater | F37: سخان الماء
A38: Doors | F38: الأبواب
A39: Windows | F39: النوافذ
A40: Keys | F40: المفاتيح
A41: Internet router | F41: جهاز توجيه الإنترنت
... A44: Remarks | F44: الملاحظات :
A45: ………………………………………………………………………………………………………………………………………………………………………………
A46: ………………………………………………………………………………………………………………………………………………………………………………
A47: ………………………………………………………………………………………………………………………………………………………………………………
A48: ………………………………………………………………………………………………………………………………………………………………………………
A50: Terms and conditions | D50: شروط وأحكام :
A51: These documents are an integral part of the lease agreement. It is referred to as Document No. 4. | D51: هذه المستندات جزء لا يتجزأ من اتفاقية الإيجار . يشار إليه باسم المستند رقم 4.
A52: The tenant acknowledges that he has returned the property in the above-mentioned case. | D52: يقر المستأجر بأنه أعاد العقار في الحالة المذكورة أعلاه.
A53: The tenant undertakes to pay the water and electricity bills until the reading indicated in this document. It also undertakes to be responsible for any amounts that may be added from service providers retroactively in the future as a result of their use between the received reading described in Document 1 and the reading described in this document. The lessor has the right to demand it in an amicable manner, and in case he does not respond, the lessee may take legal action with the lessee who bears all legal consequences and attorneys’ fees in full without any shortage. | D53: يتعهد المستأجر بدفع فواتير الماء والكهرباء حتى القراءة الموضحة في هذه الوثيقة. كما يتعهد بأن يكون مسؤول عن أي مبالغ قد تضاف من مقدمي الخدمة بأثر رجعي في المستقبل نتيجة لاستخدامها بين القراءة المستلمة الموضحة في المستند 1 والقراءة الموضحة في هذا المستند. يحق للمؤجر المطالبة بها بطريقة ودية ، وفي حالة عدم رده ، يجوز للمستأجر اتخاذ إجراءات قانونية مع المستأجر الذي يتحمل جميع التبعات القانونية وأتعاب المحاماة بالكامل دون أي نقص.
A54: The rental unit is received from the tenant after completing all required documents, signing the cancellation form and paying all bills and rents. The landlord may not receive the keys until all the bills have been settled and the rent arrears paid. As a result, the tenant has to pay the rent until the day of the actual eviction and the receipt of the key by the landlord. | D54: يتم استلام العقار من المستأجر بعد استكمال جميع المستندات المطلوبة وتوقيع نموذج الإلغاء ودفع جميع الفواتير والإيجارات. لا يجوز للمالك استلام المفاتيح إلا بعد تسوية جميع الفواتير ودفع متأخرات الإيجار. نتيجة لذلك ، يتعين على المستأجر دفع الإيجار حتى يوم الإخلاء الفعلي واستلام المالك للمفتاح.
A55: The amount of the security deposit is returned after liquidation of all obligations and payment of all bills, as well as in the event that there are no defects or problems with the rental unit. resulting from neglect or misuse. And that is after a maximum of one week after signing this form. | D55: يتم إرجاع مبلغ التأمين بعد تصفية جميع الالتزامات ودفع جميع الفواتير ، وكذلك في حالة عدم وجود عيوب أو مشاكل في الوحدة المؤجرة. الناتجة عن الإهمال أو سوء الاستخدام. وذلك بعد أسبوع كحد أقصى بعد توقيع هذا النموذج.
A56: The images attached to this document are considered complementary to it and are an integral part of it, such as (images of service meters such as electricity and water, as well as images of the property itself and any other images). | D56: تعتبر الصور المرفقة بهذه الوثيقة مكملة لها وهي جزء لا يتجزأ منها مثل (صور عدادات الخدمة مثل الكهرباء والماء وكذلك صور العقار نفسه وأي صور أخرى).
A57: The tenant's signature on this form is evidence of everything contained therein, and he is responsible for it before the competent authorities. | D57: يعد توقيع المستأجر على هذا النموذج دليلاً على كل ما ورد فيها ، وهو مسؤول عنه أمام الجهات المختصة.

Sheet 06- TENANCY CANCELLATION
A4: مجموعة سيد فياض العالمية ش م م
A5: SYED FAYYAZ GROUP INTERNATIONAL L L C
A6: ص.ب: 154 ، الرمز البريدي : 111 ،سلطنة عمان ، هاتف : 2449944841 968 + ، فاكس 24497482 968 +
A7: P.O.Box : 154 , P.C : 111 ,Sultanate of Oman, Tel.: +968 24499481 Fax.: +968 24497482
A8: Mr. | C8: الفاضل / المحترم
A9: Mr. Director of Contracts Department | C9: الفاضل / مدير دائرة العقود المحترم
A10: TENANCY CANCELLATION ( Document No. 7 ) | C10: طلب الغـــاء عقـــــد الايــجـــار ( مستند رقم 7 )
A11: Agreement No.: | B11: ='01- Residential'!C11 -> 20241115892 | D11: رقم العقد :
A12: Tenant Details (Second Party): | C12: بيانات المستأجر (الطرف الثاني ) :
A13: Name: | B13: ='01- Residential'!C16 -> Ljina Sultan Sulaiman AlMahrouqi | D13: الاسم:
A14: ID / Labor Card No.: | B14: ='01- Residential'!C17 -> 5640721 | D14: الرقم المدني / رقم بطاقة العمل :
A15: Mobile No | B15: ='01- Residential'!D19 -> 91707091 | D15: رقم النقال :
A16: Property Details: | C16: بيانات العقار المستأجر :
A17: Building No.: | B17: ='01- Residential'!C23 -> MQ Plot 369, Building 5240 | D17: رقم المبنى :
A18: Flat/Shop no : | B18: ='01- Residential'!C26 -> 301 | D18: رقم الشقة/المحل :
A19: Date of termination of the tenancy agreement | C19: تاريخ إنهاء عقد الإيجار
A20: Date | B20: 19/08/2022 | D20: التاريخ
A21: I, the undersigned, certify that I am a tenant of the above-mentioned property, in accordance with the rental agreement concluded with the property owner, and because I do not wish to continue renting the property, I declare that the above-mentioned unit contract is null and void and does not entail any legal effects for me the rented unit, as of My signature on this letter, unless I do not settle the electricity, water and rent bills, this request is considered void and the place is my responsibility until I pay all the obligations and arrears and I must pay the rent until the day of handing over the property with all obligations settled. | C21: أنا الموقع أدناه أقر بأنني مستأجر للعقار المذكور بياناته أعلاه ، وذلك وفقًا لاتفاقية الإيجار المبرمة مع مالك العقار ، ولأنني لا أرغب في مواصلة في استأجار العقار ، أقر بأن عقد الوحدة المذكورة أعلاه باطل ولاغٍ ولا يترتب عليه أي آثار قانونية بالنسبة لي الوحدة المستأجرة ، اعتبارًا من توقيعي على هذا الخطاب ، إلا إذا لم اقم بتسوية فواتير الكهرباء والماء والإيجار ، هذا يعتبر الطلب باطلاً ويعتبر المكان على مسؤوليتي حتى أقوم بسداد جميع الالتزامات والمتأخرات ويجب علي دفع الإيجار حتى يوم تسليم العقار مع تسوية جميع الالتزامات. .
A22: I also acknowledge that the owner, his agent, or his representative has the full right to rent the property whose contract has expired to whomever he wants at any time he wants it as he wants after the date of my signature on this letter, and he has the right to cut off electricity and water from the property immediately upon the termination of the aforementioned contract without referring to me, I waive my right to any objection or claim of rights. | C22: أقر أيضًا بأن للمالك أو وكيله أو من ينوب عنه الحق الكامل في تأجير العقار الذي انتهى عقده لمن يريد في أي وقت يريده كما يشاء بعد تاريخ توقيعي على هذه الرسالة ، ولديه الحق في قطع الكهرباء والماء عن العقار فور فسخ العقد سالف الذكر دون الرجوع إلي ، أتنازل عن حقي في أي اعتراض أو مطالبة بحقوق.
A23: I also acknowledge that the owner, his agent or his representative has the full right to throw everything inside the property, use it or resell it if he wishes to do so, unless I take it until the date of signing this document and I pledge not to claim from them whether it is a financial claim or any other claim. | C23: أقر أيضًا بأن للمالك أو وكيله أو من ينوب عنه له الحق الكامل في إلقاء كل ما هو داخل العقار أو استخدامه أو إعادة بيعه إذا رغب في ذلك ، ما لم آخذه حتى تاريخ توقيع هذه الوثيقة وأتعهد بعدم المطالبي لهم سواء كانت مطالبة مالية أو أية مطالبة أخرى..
A24: I also acknowledge that after signing this letter, I have no right of any kind in the property referred to above, whether it is a suspension of the right to lease or otherwise, and that the termination of the contract is on my responsibility. | C24: كما اقر بانني بعد توقيعي لهذا الخطاب ، ليس لي أي حق مهما كان نوعه في العقار المشار اليه أعلاه ، سواء تعليق في حق الإجارة أو غير ذلك وان فسخ العقد على مسؤوليتي .
A25: I fully acknowledge the contents of this application and sign it. | C25: أقر تمامًا بمحتويات هذا الطلب وأوقعه.

Sheet الشروط و الاحكام 
A4: مجموعة سيد فياض العالمية ش م م
A5: SYED FAYYAZ GROUP INTERNATIONAL L L C
A6: ص.ب: 154 ، الرمز البريدي : 111 ، سلطنة عمان ، هاتف : 2449944841 968 + ، فاكس 24497482 968 +
A7: P.O.Box : 154 , P.C : 111 ,Sultanate of Oman, Tel.: +968 24499481 Fax.: +968 24497482
A9: Extension of Tenancy Agreement (Document No. 2-A ) | D9: ملحق عقد إيجار ( مستند رقم 2 - أ )
A10: Agreement No.: | C10: ='01- Residential'!C11 -> 20241115892 | E10: رقم العقد :
A11: Terms and conditions for renting units ( personal ) | D11: الشروط والأحكام لتأجير للوحدات ( الشخصية )
A12: 1 | B12: Official Communication Method | D12: طريقة الاتصال الرسمية | F12: 1
A13: A | B13: All official communication must be delivered in writing by hand or the registered email addresses in this agreement. | D13: يجب تسليم جميع المراسلات الرسمية الكتابة باليد أو عناوين البريد الإلكتروني المسجلة في هذه الاتفاقية. | F13: أ
A14: 2 | B14: Non-Refundable Booking Deposit | D14: وديعة الحجز غير قابلة للاسترداد | F14: 2
A15: A | B15: In case the Tenant does not proceed with renting the Unit, the non-refundable booking deposit will be forfeited. | D15: في حالة عدم قيام المستأجر باستئجار الوحدة ، سيتم مصادرة وديعة الحجز غير القابلة للاسترداد. | F15: أ
A16: B | B16: Once this agreement is signed and the Tenant has paid the rent for the first month of the tenancy agreement, the non-refundable booking deposit will automatically be converted to a security deposit. | D16: بمجرد توقيع هذه الاتفاقية ودفع المستأجر إيجار الشهر الأول من اتفاقية الإيجار ، سيتم تحويل وديعة الحجز غير القابلة للاسترداد تلقائيًا إلى وديعة تأمين. | F16: ب
A17: 3 | B17: Security Deposit | D17: مبلغ التأمين | F17: 3
A18: A | B18: The Tenant is required to deposit and maintain one month’s rent as a security deposit throughout the tenancy period. | D18: يتعين على المستأجر إيداع إيجار شهر واحد والاحتفاظ به كوديعة ضمان طوال فترة الإيجار. | F18: أ
A19: B | B19: The security deposit is refundable subject to the Tenant completing their full tenancy period as per the agreement and clearing all their dues. | D19: وديعة الضمان قابلة للاسترداد بشرط استكمال المستأجر لفترة الإيجار الكاملة وفقًا للاتفاقية وتسوية جميع مستحقاته. | F19: ب
A20: C | B20: If the tenancy agreement is terminated early for any reason, the security deposit will be forfeited. | D20: إذا تم إنهاء عقد الإيجار مبكرًا لأي سبب من الأسباب ، فسيتم مصادرة وديعة التأمين. | F20: ت
A21: 4 | B21: Payment Terms | D21: شروط الدفع | F21: 4
A22: A | B22: The Tenant must pay the due rent on the 01st of the month in advance. | D22: يجب على المستأجر دفع الإيجار المستحق في اليوم الأول من الشهر مقدمًا. | F22: أ
A23: B | B23: The Tenant must provide post-dated cheques for the entire duration of the tenancy agreement. | D23: يجب على المستأجر تقديم شيكات مؤجلة الدفع لكامل مدة عقد الإيجار. | F23: ب
A24: C | B24: The Tenant must provide 3 additional open-dated cheques equivalent to 3 months of rent. These will be deposited by the Landlord in case of any outstanding rent or other dues. | D24: يجب على المستأجر تقديم 3 شيكات إضافية مفتوحة الدفع تعادل 3 أشهر من الإيجار. سيتم إيداعها من قبل المالك في حالة وجود أي إيجار مستحق أو مستحقات أخرى. | F24: ت
A25: D | B25: If the Tenant prefers to pay the rent by a bank transfer instead, the payment should be cleared at least three working days prior to the rent due date. Moreover, the Tenant should inform the Landlord once the bank transfer is completed by an official communication method. | D25: إذا فضل المستأجر دفع الإيجار عن طريق التحويل المصرفي بدلاً من ذلك ، فيجب تسوية الدفع قبل ثلاثة أيام عمل على الأقل من تاريخ استحقاق الإيجار. علاوة على ذلك ، يجب على المستأجر إبلاغ المالك بمجرد اكتمال التحويل المصرفي بطريقة اتصال رسمية. | F25: ث
A26: E | B26: The cheque deposit date is the 01st of the month. In case the Tenant’s cheque bounces on the 01st, the Landlord will deposit it again on the 10th of the month, unless the Tenant has cleared the rent by bank transfer prior to the 10th. | D26: تاريخ إيداع الشيك هو الأول من الشهر. في حالة ارتداد الشيك الخاص بالمستأجر في اليوم الأول ، سيقوم المالك بإيداعه مرة أخرى في اليوم العاشر من الشهر ، إلا إذا قام المستأجر بتخليص الإيجار عن طريق التحويل المصرفي قبل اليوم العاشر. | F26: ج
A27: F | B27: If the Tenant's cheques bounce due to insufficient funds, a penalty of 5% of the cheque amount will be charged by the Landlord. | D27: إذا ارتد شيك المستأجر بسبب عدم كفاية الأموال ، سيتم فرض غرامة قدرها 5 ٪ من مبلغ الشيك من قبل المالك. | F27: ح
A28: 5 | B28: Late Payments | D28: المدفوعات المتأخرة | F28: 5
A29: A | B29: If the rent is not received by the 15th of the month, a 15% late fee penalty will be charged on the cheque value on the 15th of the month. | D29: إذا لم يتم استلام الإيجار بحلول الخامس عشر من الشهر ، فسيتم فرض غرامة تأخير قدرها 15٪ على قيمة الشيك في الخامس عشر من الشهر. | F29: أ
A30: B | B30: An additional 1% late fee penalty will be charged for every additional day of delay in rent after the 15th of the month, .e.g. a 17% late fee penalty if the rent is not paid until the 17th of the month. | D30: سيتم فرض غرامة إضافية بنسبة 1٪ على رسوم التأخير عن كل يوم تأخير إضافي في الإيجار بعد اليوم الخامس عشر من الشهر ، على سبيل المثال. غرامة 17٪ رسوم تأخير إذا لم يتم دفع الإيجار حتى 17 من الشهر. | F30: ب
A31: C | B31: If the late fee penalty is not paid by the end of the month, it will carry forward and accumulate with future penalty fees. | D31: إذا لم يتم دفع غرامة الرسوم المتأخرة بحلول نهاية الشهر ، فسيتم ترحيلها وتتراكم مع رسوم الغرامات المستقبلية. | F31: ت
A32: 6 | B32: Utility Bills | D32: فواتير المياه والكهرباء | F32: 6
A33: A | B33: The Tenant is required to pay all utility bills of their Unit in full every month. | D33: يتعين على المستأجر دفع جميع فواتير المرافق الخاصة بوحدته بالكامل كل شهر. | F33: أ
A34: B | B34: If the Tenant’s combined bills for water and electricity accumulate to over 25% of their monthly rent, the Landlord has the right to disconnect the electricity and water of the Unit and take legal action. The pending bill amount may also be deducted from the security deposit.With the tenant bearing all the legal consequences and losses that he may incur as a result of cutting the service for him. | D34: إذا تراكمت فواتير المستأجر المجمعة للمياه والكهرباء لأكثر من 25٪ من الإيجار الشهري ، يحق للمالك فصل الكهرباء والمياه عن الوحدة واتخاذ الإجراءات القانونية. قد يتم أيضًا خصم مبلغ الفاتورة المعلقة من وديعة التأمين. مع تحمل المستأجر كافة التبعات القانونية والخسائر التي قد يتكبدها نتيجة قطع الخدمة عنه. | F34: ب
A35: C | B35: In case the Landlord pays the utility bills on the Tenant's behalf, a service charge of 5% of the monthly rent will be charged. | D35: في حالة قيام المالك بدفع فواتير الخدمات نيابة عن المستأجر ، سيتم فرض رسوم خدمة بنسبة 5٪ من الإيجار الشهري. | F35: ت
A36: 7 | B36: Conditions of Stay | D36: شروط الاقامة | F36: 7
A37: A | B37: The Tenant shall abide by all the instructions issued by the Landlord, which may change throughout the tenancy agreement. | D37: يجب على المستأجر الالتزام بجميع التعليمات الصادرة عن المالك ، والتي قد تتغير خلال عقد الإيجار. | F37: أ
A38: B | B38: The Tenant is not allowed to sublet the Unit. | D38: لا يجوز للمستأجر تأجير الوحدة من الباطن. | F38: ب
A39: C | B39: The Unit will be occupied only by the Tenant and their immediate family, and used only for residential purposes. | D39: سيتم شغل الوحدة من قبل المستأجر وعائلته المباشرة فقط ، وسيتم استخدامها فقط للأغراض السكنية. | F39: ت
A40: D | B40: The Tenant will not make any changes to the leased Unit without approval from the Landlord. In case any changes are made without the Landlord's approval, the Landlord has the right to cancel the tenancy agreement. | D40: لن يقوم المستأجر بإجراء أي تغييرات على الوحدة المؤجرة دون موافقة المالك. في حالة إجراء أي تغييرات دون موافقة المالك ، يحق للمالك إلغاء عقد الإيجار. | F40: ث
A41: E | B41: The Tenant must return the Unit at the end of their tenancy agreement in the original condition that they received it in at the start of the tenancy agreement. Failure to do so will require the Landlord to charge all the costs to the Tenant to do such work. | D41: يجب على المستأجر إعادة الوحدة في نهاية عقد الإيجار إلى الحالة الأصلية التي استلمها بها في بداية عقد الإيجار. إن عدم القيام بذلك سوف يتطلب من المالك تحميل جميع التكاليف على المستأجر للقيام بهذا العمل. | F41: ج
A42: F | B42: The Tenant will be liable for any damage occurring to their Unit or the entire Property which is done by the Tenant or the Tenant’s guests or invitees. | D42: سيكون المستأجر مسؤولاً عن أي ضرر يحدث لوحدته أو العقار بأكمله والذي يحدث من قبل المستأجر أو ضيوف المستأجر أو المدعوين. | F42: ح
A43: G | B43: The Tenant will not place any items outside of their leased Unit, including but not limited to the public areas, such as corridors, elevators, staircase, basements and roof floor. | D43: لن يضع المستأجر أي عناصر خارج الوحدة المؤجرة ، بما في ذلك على سبيل المثال لا الحصر المناطق العامة ، مثل الممرات والمصاعد والسلالم والطوابق السفلية وأرضية السقف. | F43: خ
A44: H | B44: The Tenant shall maintain the property in a manner which conforms to all health and safety requirements. The Tenant shall keep their Unit free from all rodents, insects, and vermin attracted by unsanitary conditions caused by Tenant, and shall be responsible for all damage caused by such conditions. | D44: يجب على المستأجر صيانة العقار بطريقة تتوافق مع جميع متطلبات الصحة والسلامة. يجب على المستأجر الحفاظ على وحدته خالية من جميع القوارض والحشرات والحشرات التي تجذبها الظروف غير الصحية التي يسببها المستأجر ، ويكون مسؤولاً عن جميع الأضرار التي تسببها هذه الظروف. | F44: د
A45: I | B45: The Tenant will not litter or throw garbage in any part of the entire Property, or throw anything out of the windows, doors or ventilating ducts. | D45: لا يجوز للمستأجر إلقاء القمامة أو إلقاء القمامة في أي جزء من العقار بأكمله ، أو إلقاء أي شيء من النوافذ أو الأبواب أو قنوات التهوية. | F45: ذ
A46: J | B46: The Tenant shall not permit or allow any vehicles that belong to or are controlled by the Tenant or their employees, suppliers, customers or invitees to be loaded, unloaded or parked in the Property in areas not approved by the Landlord. Not abiding by this will be classified as a Parking Violation. | D46: يجب ألا يسمح المستأجر أو يسمح بأي مركبات تخص المستأجر أو يتحكم فيه أو موظفيه أو مورديه أو زبائنه أو مدعويهم أو تفريغها أو ركنها في العقار في مناطق لم يوافق عليها المالك. عدم الالتزام بهذا سوف يصنف على أنه مخالفة وقوف. | F46: ر
A47: K | B47: The Tenant will not cause excessive noise and disturbances to other occupants of the Property, especially during late hours. The Landlord will notify the Tenant of such complaints. | D47: لن يتسبب المستأجر في إحداث ضوضاء وإزعاج مفرطة لشاغلي العقار الآخرين ، خاصة خلال ساعات العمل المتأخرة. يقوم المالك بإخطار المستأجر بهذه الشكاوى. | F47: ز
A48: 8 | B48: Violations of Conditions | D48: مخالفات الشروط | F48: 8
A49: A | B49: In case the Tenant does not abide by any conditions of stay, the Landlord has the right to impose a penalty of 5% of the monthly rent per violation, per day. | D49: في حالة عدم التزام المستأجر بأي شروط للإقامة ، يحق للمالك فرض غرامة قدرها 5٪ من الإيجار الشهري لكل مخالفة في اليوم. | F49: أ
A50: B | B50: If the Tenant does not resolve the violation immediately, a daily penalty of 5% of the monthly rent will be imposed for each day the violation continues. | D50: إذا لم يقم المستأجر بحل المخالفة على الفور ، سيتم فرض غرامة يومية قدرها 5٪ من الإيجار الشهري عن كل يوم تستمر فيه المخالفة. | F50: ب
A51: C | B51: If a specific violation exceeds 1 month from the date of warning, or if the Tenant receives signicant violations during their tenancy period, the Landlord has the right to terminate the lease agreement and the Tenant should vacate the unit immediately. Failure to do so will result in legal action being taken. | D51: إذا تجاوز الانتهاك المحدد شهرًا واحدًا من تاريخ التحذير ، أو إذا تلقى المستأجر انتهاكات جسيمة خلال فترة الإيجار ، يحق للمالك إنهاء عقد الإيجار ويجب على المستأجر إخلاء الوحدة على الفور. سيؤدي عدم القيام بذلك إلى اتخاذ إجراءات قانونية. | F51: ت
A52: D | B52: In case of a Parking Violation by the Tenant, along with the daily penalty of 5% of the monthly rent, the Landlord shall have the right, without notice, to remove or tow away the vehicle involved and charge the costs to the Tenant. | D52: في حالة مخالفة المستأجر لوقوف السيارات ، بالإضافة إلى الغرامة اليومية البالغة 5٪ من الإيجار الشهري ، يحق للمالك ، دون سابق إنذار ، إزالة أو سحب السيارة المعنية وتحميل التكاليف على المستأجر. | F52: ث
A53: 9 | B53: Access Cards and Building Amenities | D53: بطاقات الوصول ووسائل الراحة في المبنى | F53: 9
A54: A | B54: The Landlord has the right to disconnect the Tenant's building access cards and all other amenities anytime in case the Tenant does not by abide by any of their tenancy requirements. | D54: يحق للمالك فصل بطاقات الوصول إلى المبنى الخاصة بالمستأجر وجميع وسائل الراحة الأخرى في أي وقت في حالة عدم التزام المستأجر بأي من متطلبات الإيجار الخاصة بهم. | F54: أ
A55: 10 | B55: Legal Action | D55: إجراءات قانونية | F55: 10
A56: A | B56: The Tenant will be liable for all legal expenses borne by the Landlord in case of any violation of this tenancy. | D56: سيكون المستأجر مسؤولاً عن جميع النفقات القانونية التي يتحملها المالك في حالة حدوث أي انتهاك لهذا الإيجار. | F56: أ
A57: 11 | B57: Maintenance and Repairs | D57: الصيانة والتصليح | F57: 11
A58: A | B58: Tenant agrees to keep their Unit clean and takes responsibility for damages, window cleaning and all minor repairs. Minor repairs include replacing batteries, light bulbs and tubes. | D58: يوافق المستأجر على الحفاظ على نظافة وحدته ويتحمل مسؤولية الأضرار وتنظيف النوافذ وجميع الإصلاحات الطفيفة. تشمل الإصلاحات البسيطة استبدال البطاريات والمصابيح الكهربائية والأنابيب. | F58: أ
A59: 12 | B59: Right of Entry | D59: حق الدخول | F59: 12
A60: A | B60: In case of emergencies, the Landlord will attempt to contact the Tenant. If no response is received, the Landlord has the right to enter the Unit. | D60: في حالة الطوارئ ، سيحاول المالك الاتصال بالمستأجر. في حالة عدم تلقي أي رد ، يحق للمالك دخول الوحدة. | F60: أ
A61: 13 | B61: Tenancy Renewal | D61: تجديد الإيجار | F61: 13
A62: A | B62: The Landlord has the right to increase the monthly rent indefinitely during the tenancy renewal. | D62: للمالك الحق في زيادة الإيجار الشهري إلى أجل غير مسمى خلال تجديد عقد الإيجار. | F62: أ
A63: B | B63: Before renewing the tenancy agreement, the Tenant will provide all required documentation, security deposit and post-dated cheques. Without these, the Tenant will be unable to renew their tenancy agreement. | D63: قبل تجديد عقد الإيجار ، سيقدم المستأجر جميع المستندات المطلوبة ووديعة الضمان والشيكات المؤجلة. بدون هذه الشروط ، لن يتمكن المستأجر من تجديد عقد الإيجار الخاص به. | F63: ب
A64: C | B64: In case of a delay in renewal of the tenancy agreement due to the Tenant, the Tenant will be liable for the Muncipality renewal fee and all Municipality fines. | D64: في حالة التأخير في تجديد عقد الإيجار بسبب المستأجر ، سيكون المستأجر مسؤولاً عن رسوم تجديد البلدية وجميع غرامات البلدية. | F64: ت
A65: 14 | B65: Vacating the Unit | D65: إخلاء الوحدة | F65: 14
A66: A | B66: The Tenant must complete the full period of the tenancy agreement. | D66: يجب على المستأجر إكمال الفترة الكاملة لعقد الإيجار. | F66: أ
A67: B | B67: If the Tenant wishes to vacate the Unit at the end of their tenancy agreement, a 90-day notice must be given to the Landlord by an official communication method. | D67: إذا رغب المستأجر في إخلاء الوحدة في نهاية عقد الإيجار ، فيجب تقديم إشعار لمدة 90 يومًا إلى المالك من خلال وسيلة اتصال رسمية. | F67: ب
A68: C | B68: If the tenant gives less than a 90-day notice to vacate the Unit at the end of their tenancy agreement, the Tenant will be liable for rent for 90 days from the date of their official notice. | D68: إذا قدم المستأجر إشعارًا مدته أقل من 90 يومًا لإخلاء الوحدة في نهاية اتفاقية الإيجار ، فسيكون المستأجر مسؤولاً عن الإيجار لمدة 90 يومًا من تاريخ إخطاره الرسمي. | F68: ت
A69: D | B69: The Landlord has the right to refuse the handover of the Unit after the end of the tenancy period if the Tenant has not cleared all their dues in full, including but not limited to: rent, utility bills and penalty fees. | D69: يحق للمالك رفض تسليم الوحدة بعد نهاية فترة الإيجار إذا لم يقم المستأجر بتصفية جميع مستحقاته بالكامل ، بما في ذلك على سبيل المثال لا الحصر: الإيجار وفواتير الخدمات ورسوم الغرامات. | F69: ث
A70: E | B70: The Tenant will be obligated to pay rent and utility bills until the handover is completed by the Landlord. | D70: يلتزم المستأجر بدفع فواتير الإيجار والمرافق حتى اكتمال التسليم من قبل المالك. | F70: ج
A71: 15 | B71: Handover of Unit | D71: تسليم الوحدة | F71: 15
A72: A | B72: The Tenant must complete the handover form and return all keys and access cards to the Landlord's office before the tenancy agreement can be ended. The Landlord will issue a clearance form once this is completed. Without the clearance form, the Tenant will continue to be liable for all dues, including rent and utility bills. | D72: يجب على المستأجر إكمال نموذج التسليم وإعادة جميع المفاتيح وبطاقات الوصول إلى مكتب المالك قبل إنهاء عقد الإيجار. سيصدر المالك استمارة براءة ذمة بمجرد اكتمال ذلك. بدون نموذج التخليص ، سيظل المستأجر مسؤولاً عن جميع المستحقات ، بما في ذلك فواتير الإيجار والمرافق. | F72: أ
A73: B | B73: The Tenant must return the Unit in the same condition that it was received at the start of the tenancy. Failure to do so will result in charges to the Tenant. | D73: يجب على المستأجر إعادة الوحدة بنفس الحالة التي تم استلامها بها في بداية عقد الإيجار. سيؤدي عدم القيام بذلك إلى فرض رسوم على المستأجر. | F73: ب
A74: C | B74: The Tenant must have the Unit deep cleaned prior to handover. Failure to do so will result in a cleaning fee charged to the Tenant. | D74: يجب على المستأجر تنظيف الوحدة بعمق قبل التسليم. سيؤدي عدم القيام بذلك إلى فرض رسوم تنظيف على المستأجر. | F74: ت
A75: D | B75: The Tenant will be responsible for any damages to the Unit or overall Property. | D75: سيكون المستأجر مسؤولاً عن أي أضرار تلحق بوحدة الملكية العامة. | F75: ث
A76: E | B76: If the Tenant does not handover the Unit after the expiration of the tenancy agreement, they will be liable for a penalty fee of 3% of the monthly rent for every day, as well as the actual rent value for that period. | D76: إذا لم يسلم المستأجر الوحدة بعد انتهاء عقد الإيجار ، فسيكون مسؤولاً عن دفع غرامة قدرها 3٪ من الإيجار الشهري لكل يوم ، بالإضافة إلى قيمة الإيجار الفعلية لتلك الفترة. | F76: ج
A77: 16 | B77: Fees and Taxes | D77: الرسوم والضرائب | F77: 16
A78: A | B78: The Tenant is liable for all fees and taxes imposed by the government, including but not limited to VAT. | D78: المستأجر مسؤول عن جميع الرسوم والضرائب التي تفرضها الحكومة ، بما في ذلك على سبيل المثال لا الحصر ضريبة القيمة المضافة. | F78: أ
A79: 17 | B79: Severability Clause | D79: شرط الفصل | F79: 17
A80: A | B80: In case any provision in this agreement shall be invalid, the validity of the remaining terms and conditions shall not be impaired in any way. | D80: في حالة عدم صلاحية أي حكم في هذه الاتفاقية ، لن يتم المساس بصلاحية الشروط والأحكام المتبقية بأي شكل من الأشكال. | F80: أ

Sheet ورقة1
A1: سيد فياض بن علي - Syed Fayyaz ali | B1: هناء بنت سيد فياض - Hana Syed Fayyaz | C1: Ali Salim Al Sinani - علي بن سالم السناني | D1: أحمد بن هاشل المسكري - Ahmad Hashil Al Muskri | E1: Syed Fayyad & Abdul Qader سيد فياض و عبد القادر | F1: Wafa Ali Slaim Al Sinani - وفاء بنت علي بن سالم السناني | G1: زكية بنت محمد بن خميس الزدجالي Zakat Muhammad Khamis Al-Zadjali | H1: محمد بن سيد فياض - Mohammad Syed Fayyaz | I1: Husin Ali Al Sinani - حسين بن علي السناني
B2: تجديد Renewal | C2: New جديد
B3: سكني Residential | C3: تجاري Commercial
A4: Azaiba Plot 54, Building 65 | B4: Barka Plot 1248, Building 999 | C4: MQ Plot 36, Building 2645 | D4: Azaiba Plot 170, Building 638 | E4: Azaiba Plot 108, Building 449 | F4: Al Khuwair Plot 410, Building 88 | G4: Darsait Plot 109, Building 536 | H4: Ghubrah Plot 160/2, Building 1114 | I4: Ghubrah Plot 160/3, Building 1116 | J4: Ghubrah Plot 840, Building 225 | K4: Ghubrah Plot 1608, Building 7100 | L4: Mabella Plot 11, Building 75 | M4: Ruwi Plot 381, Building 37 | N4: Ruwi Plot 140, Building 771 | O4: Ali Salim Properties - Various | P4: Wafa Ali Salim Villa | Q4: Zakat FLAT 506 BUILDING 1440 | R4: Mabella Plot 3, Building 180 | S4: MQ Plot 369, Building 5240
A5: نقدا Cash | B5: شيك CHQ | C5: تحويل بنكي Bank transfer
A6: نقدا Cash | B6: شيك CHQ | C6: تحويل بنكي Bank transfer | D6: لا يوجد Nothing
C12: `
